Workbook
Name AAH_abatt_general: [1]Barème!$B$152
Name AAH_abatt_salaire_t1: [1]Barème!$B$153
Name AAH_abatt_salaire_t2: [1]Barème!$B$154
Name AAH_cplmt_ressources: [1]Barème!$B$149
Name AAH_montant: [1]Barème!$B$148
Name AAH_mva: [1]Barème!$B$150
Name AAH_plaf_couple: [1]Barème!$B$145
Name AAH_plaf_seul: [1]Barème!$B$144
Name AAH_plaf_sup_pac: [1]Barème!$B$146
Name AAH_plafond_abatt_salaire: [1]Barème!$B$155
Name abatt_rbg_are: [1]Barème!$B$140
Name abatt_rfr: [1]Barème!$B$280
Name abt_th_4demipart: [1]Barème!$B$273
Name abt_th_base: [1]Barème!$B$272
Name abt_th_demipartsup: [1]Barème!$B$274
Name AF_2enft: [1]Barème!$B$34
Name AF_enft_sup: [1]Barème!$B$35
Name al_taux_compl: [1]Barème!$B$51
Name APL_abatt_biactifs: [1]Barème!$B$70
Name APL_batt_biactifs: [1]Barème!$B$70
Name ars11_14: [1]Barème!$B$74
Name ars15_18: [1]Barème!$B$75
Name ars6_10: [1]Barème!$B$73
Name assiette_PS_ARE: [1]Barème!$B$256
Name bmaf: [1]Barème!$B$93
Name bmaf_n_1: [1]Barème!$B$92
Name bmaf_n_2: [1]Barème!$B$91
Name deflat: [1]Barème!$B$289
Name deflat_2: [1]Barème!$B$292
Name deflat_3: [1]Barème!$B$291
Name forf_logement_rsa_1: [1]Barème!$B$19
Name forf_logement_rsa_2: [1]Barème!$B$20
Name forf_logement_rsa_3: [1]Barème!$B$21
Name majo_age_AF: [1]Barème!$B$36
Name majo_enf_ppe: [1]Barème!$B$201
Name majo_mono_act_ppe: [1]Barème!$B$200
Name majo_mono_ppe: [1]Barème!$B$200
Name majo_monoact_ppe: [1]Barème!$B$200
Name majo_monoparent_ppe: [1]Barème!$B$202
Name majo_tp_ppe: [1]Barème!$B$199
Name max_mono_ppe: [1]Barème!$B$194
Name max_mono_ppe_inf: [1]Barème!$B$193
Name max_ppe: [1]Barème!$B$192
Name min_ppe: [1]Barème!$B$190
Name mod_cotis_fam: [1]Barème!$B$248
Name mont_ASF_RSA: [1]Barème!$B$96
Name mont_ASF_total: [1]Barème!$B$95
Name mont_decote_celib: [1]Barème!$B$172
Name mont_decote_couple: [1]Barème!$B$173
Name mont_forfaitaire_rsa: [1]Barème!$B$10
Name mont_forfaitaire_rsa_majo: [1]Barème!$B$15
Name mont_th_couple: [1]Barème!$B$266
Name montant_acs_0_15: [1]Barème!$B$121
Name montant_acs_16_49: [1]Barème!$B$122
Name montant_acs_à_15: [1]Barème!$B$121
Name montant_CF: [1]Barème!$B$81
Name montant_CF_majo: [1]Barème!$B$86
Name montant_cmuc_0_15: [1]Barème!$B$125
Name montant_cmuc_16_49: [1]Barème!$B$126
Name montant_elec_1p: [1]Barème!$B$134

Sheet Figure 1
A1: Figure 1 - Transferts publics depuis 1949 en part du revenu national brut
F2: en % du revenu national brut
B3: Taxes sur les produits et la production | C3: Impôts sur les revenus et le patrimoine | D3: Cotisations sociales | E3: Prestations en espèces | F3: Transferts en nature | G3: Consommation collective
A4: 1949 | B4: -12.7 | C4: -3.8 | D4: -10.5 | E4: 10 | F4: 9.3 | G4: 7.2
A5: =A4+1 -> 1950 | B5: -13.3 | C5: -4.2 | D5: -10.7 | E5: 10.4 | F5: 9.3 | G5: 7.3
A6: =A5+1 -> 1951 | B6: -13.8 | C6: -4.1 | D6: -10.6 | E6: 10.4 | F6: 9.4 | G6: 7.3
A7: =A6+1 -> 1952 | B7: -14.3 | C7: -4.2 | D7: -11 | E7: 10.4 | F7: 9.9 | G7: 7.8
A8: =A7+1 -> 1953 | B8: -14.3 | C8: -5.1 | D8: -11.4 | E8: 10.9 | F8: 10.2 | G8: 8
A9: =A8+1 -> 1954 | B9: -14 | C9: -4.5 | D9: -11.6 | E9: 11.1 | F9: 9.9 | G9: 7.6
A10: =A9+1 -> 1955 | B10: -13.4 | C10: -4.2 | D10: -11.9 | E10: 11.6 | F10: 9.7 | G10: 7.2
A11: =A10+1 -> 1956 | B11: -13.2 | C11: -4.8 | D11: -12.2 | E11: 11.6 | F11: 10 | G11: 7.6
A12: =A11+1 -> 1957 | B12: -13.5 | C12: -4.9 | D12: -11.9 | E12: 11.5 | F12: 9.8 | G12: 7.4
A13: =A12+1 -> 1958 | B13: -13.8 | C13: -5.5 | D13: -11.9 | E13: 11.2 | F13: 9.6 | G13: 7.2
A14: =A13+1 -> 1959 | B14: -14.6 | C14: -5.7 | D14: -12.3 | E14: 11.4 | F14: 9.8 | G14: 7.2
A15: =A14+1 -> 1960 | B15: -14.3 | C15: -5.4 | D15: -12.1 | E15: 11.3 | F15: 9.5 | G15: 6.8
A16: =A15+1 -> 1961 | B16: -14.1 | C16: -5.4 | D16: -13.1 | E16: 11.6 | F16: 9.8 | G16: 6.9
... A74: =A73+1 -> 2019 | B74: -13.7 | C74: -12.6 | D74: -18.8 | E74: 21 | F74: 16.8 | G74: 7.9
A75: Note : les transferts sont rapportés au revenu national brut (RNB) et non au revenu national net (RNN), car la série depuis 1949 n'est disponible que pour le RNB.
A76: Lecture : en 2018, les prestations en espèces représentent 21 % du revenu national brut.
A77: Champ : France.
A78: Source : Insee, Comptes nationaux ; calcul des auteurs.

Sheet Figure 2
A1: Figure 2 - Comptes nationaux distribués pour la France en 2018 par dixième de niveau de vie usuel
B3: Total | D3: Transferts par dixième de population (en % du montant du transfert)
B4: en milliards | C4: en euros par UC | D4: Inférieur à D1 | E4: D1 à D2 | F4: D2 à D3 | G4: D3 à D4 | H4: D4 à D5 | I4: D5 à D6 | J4: D6 à D7 | K4: D7 à D8 | L4: D8 à D9 | M4: Supérieur à D9
A5: Revenus primaires élargis | B5: 1982.3 | C5: 42820 | D5: 2.4 | E5: 3.7 | F5: 5 | G5: 6.1 | H5: 7.3 | I5: 8.5 | J5: 9.8 | K5: 11.6 | L5: 14.3 | M5: 31.5
A6: dont : revenus salariaux bruts | B6: 1252.8 | C6: 27060 | D6: 1.7 | E6: 3.5 | F6: 5 | G6: 6.6 | H6: 8.1 | I6: 9.4 | J6: 11 | K6: 13.1 | L6: 15.7 | M6: 25.9
A7: revenus du patrimoine et mixtes1 | B7: 428.4 | C7: 9250 | D7: 1.8 | E7: 2.2 | F7: 3.1 | G7: 3.5 | H7: 4 | I7: 4.7 | J7: 5.8 | K7: 7.2 | L7: 10.5 | M7: 57.3
A8: Taxes sur les produits et la production2 | B8: -324.9 | C8: -7020 | D8: 5.8 | E8: 6.6 | F8: 7.3 | G8: 8.1 | H8: 9 | I8: 9.6 | J8: 10.3 | K8: 11.5 | L8: 13.6 | M8: 18.4
A9: dont : taxes sur la production | B9: -62.2 | C9: -1340 | D9: 2.5 | E9: 3.5 | F9: 5 | G9: 6 | H9: 7.6 | I9: 8.9 | J9: 10.6 | K9: 12.7 | L9: 16.2 | M9: 27.1
A10: taxes sur la consommation | B10: -217.3 | C10: -4690 | D10: 6.3 | E10: 7 | F10: 7.7 | G10: 8.4 | H10: 9.2 | I10: 9.6 | J10: 10.2 | K10: 11.3 | L10: 13.3 | M10: 17.1
A11: Impôts sur les revenus et le patrimoine2 | B11: -308 | C11: -6650 | D11: 0.8 | E11: 1.5 | F11: 2.4 | G11: 3.5 | H11: 4.5 | I11: 5.5 | J11: 7.2 | K11: 9.7 | L11: 13.7 | M11: 51.1
A12: dont : CSG | B12: -125.3 | C12: -2710 | D12: 1 | E12: 2.5 | F12: 4.2 | G12: 6.1 | H12: 7.7 | I12: 9.1 | J12: 10.5 | K12: 12.6 | L12: 15.9 | M12: 30.3
A13: impôts sur les revenus | B13: -83 | C13: -1790 | D13: 0.4 | E13: 0.2 | F13: 0.2 | G13: 0.7 | H13: 1.5 | I13: 2.9 | J13: 5.7 | K13: 10.1 | L13: 17 | M13: 61.2
A14: impôts sur les sociétés | B14: -59.6 | C14: -1290 | D14: 0.4 | E14: 0.5 | F14: 0.4 | G14: 0.3 | H14: 0.4 | I14: 0.5 | J14: 1.2 | K14: 2.3 | L14: 3.4 | M14: 90.5
A15: Cotisations sociales2 | B15: -478.6 | C15: -10340 | D15: 2.2 | E15: 3.8 | F15: 5.1 | G15: 6.5 | H15: 8.2 | I15: 9.6 | J15: 11.1 | K15: 13.2 | L15: 15.8 | M15: 24.5
A16: dont : cotisations retraites | B16: -258.6 | C16: -5590 | D16: 1 | E16: 2.9 | F16: 4.6 | G16: 6.3 | H16: 8.2 | I16: 9.9 | J16: 11.7 | K16: 14.2 | L16: 16.8 | M16: 24.5
... A28: Niveau de vie élargi | B28: 1982.3 | C28: 42820 | D28: 6.4 | E28: 7.4 | F28: 7.8 | G28: 8.2 | H28: 8.5 | I28: 9 | J28: 9.6 | K28: 10.5 | L28: 12 | M28: 20.6
A29: Transferts nets (en % du revenu avant transferts) | D29: 170.8 | E29: 100.7 | F29: 58.3 | G29: 33.8 | H29: 16.3 | I29: 6.5 | J29: -1.2 | K29: -9.9 | L29: -16 | M29: -34.6
A30: Transferts nets (en % du revenu national) | D30: 4 | E30: 3.7 | F30: 2.9 | G30: 2.1 | H30: 1.2 | I30: 0.5 | J30: -0.1 | K30: -1.2 | L30: -2.3 | M30: -10.9
A31: 1. Y compris profits non distribués (encadré 3).
A32: 2. Les lignes résiduelles « dont autres » ne sont pas affichées.
A33: Note : les montants par UC par dixième de niveau de vie sont disponibiles en données complémentaires sur insee.fr ;
A34: le niveau de vie élargi n'est pas égal à la somme des revenus primaires élargis et des transferts indiqués dans ce tableau du fait de transferts résiduels (notamment l'épargne nette des admistrations publiques). Ces transferts sont disponibles en données complémentaires sur insee.fr.
A35: Lecture : les revenus primaires élargis sont de 1 982,3 milliards d'euros en 2018 en France, ce qui correpond à 42 820 euros par unité de consommation (UC). Les 10 % les plus modestes (niveau de vie usuel inférieur au 1er décile) perçoivent 2,4 % des 1 982,3 milliards d'euros de revenus primaires élargis reçus en France.
A36: Champ : France.
A37: Source : Comptes nationaux distribués 2018 ; calcul des auteurs.

Sheet Figure 3
A1: Figure 3 - Transferts moyens reçus par les ménages selon leur niveau de vie usuel
J2: en euros par unité de consommation
B3: Ensemble | C3: Inférieur à D1 | D3: D1 à D2 | E3: D2 à D3 | F3: D3 à D4 | G3: D4 à D5 | H3: D5 à D6 | I3: D6 à D7 | J3: D7 à D8 | K3: D8 à D9 | L3: Supérieur à D9
A4: Prestations et allocations monétaires | B4: 10900 | C4: 7480 | D4: 8990 | E4: 9680 | F4: 9960 | G4: 10180 | H4: 10740 | I4: 11390 | J4: 11750 | K4: 13510 | L4: 15500
A5: Retraites | B5: 7220 | C5: 1280 | D5: 3490 | E5: 5210 | F5: 6240 | G5: 6870 | H5: 7520 | I5: 8630 | J5: 9130 | K5: 11120 | L5: 12670
A6: Chômage et revenus de remplacement | B6: 1860 | C6: 1520 | D6: 1870 | E6: 1880 | F6: 1780 | G6: 1760 | H6: 1860 | I6: 1670 | J6: 1840 | K6: 1910 | L6: 2540
A7: Prestations sociales monétaires | B7: 1820 | C7: 4680 | D7: 3630 | E7: 2590 | F7: 1940 | G7: 1550 | H7: 1360 | I7: 1100 | J7: 780 | K7: 480 | L7: 290
A8: Transferts en nature individualisables | B8: 8800 | C8: 12580 | D8: 11980 | E8: 10100 | F8: 8940 | G8: 8270 | H8: 7790 | I8: 7640 | J8: 7260 | K8: 7330 | L8: 6270
A9: Dépenses collectives | B9: 4130 | C9: 4310 | D9: 4030 | E9: 3850 | F9: 3900 | G9: 3790 | H9: 3910 | I9: 3930 | J9: 4060 | K9: 4320 | L9: 5140
A10: Dépenses collectives avec autre hypothèse (dépense national en fonction du revenu disponible) | B10: 4130 | C10: 3500 | D10: 3490 | E10: 3520 | F10: 3630 | G10: 3680 | H10: 3850 | I10: 4000 | J10: 4240 | K10: 4640 | L10: 6640
A11: Dépenses collectives avec variante dépenses nationales proportionnelles1 | B11: 4130 | C11: 3800 | D11: 3730 | E11: 3670 | F11: 3710 | G11: 3720 | H11: 3850 | I11: 3970 | J11: 4160 | K11: 4500 | L11: 6100
A12: Ensemble | B12: 34720 | C12: 24370 | D12: 25000 | E12: 23630 | F12: 22800 | G12: 22240 | H12: 22440 | I12: 22970 | J12: 23070 | K12: 25160 | L12: 26910
A13: Ensemble hors retraites | B13: 27500 | C13: 23090 | D13: 21510 | E13: 18420 | F13: 16560 | G13: 15370 | H13: 14930 | I13: 14340 | J13: 13940 | K13: 14040 | L13: 14250
A14: 1. Dans cette variante, les dépenses nationales sont distribuées proportionnellement au revenu élargi hors dépenses collectives.
A15: Lecture : les 10 % des individus les plus aisés (niveau de vie usuel supérieur au 9e décile) perçoivent en moyenne 12 670 euros de pensions de retraites par unité de consommation (UC) et 5 140 euros par UC.
A16: Champ : France.
A17: Source : Comptes nationaux distribués 2018 ; calcul des auteurs.

Sheet Figure 4
A1: Figure 4 - Dépenses d'éducation par dixième de niveau de vie usuel
B3: Transferts par dixième de population (en % du montant de la filière)
B4: Ensemble (en milliards d'euros) | C4: Inférieur à D1 | D4: D1 à D2 | E4: D2 à D3 | F4: D3 à D4 | G4: D4 à D5 | H4: D5 à D6 | I4: D6 à D7 | J4: D7 à D8 | K4: D8 à D9 | L4: Supérieur à D9
A5: Primaire et secondaire | B5: 81.9 | C5: 14.6 | D5: 13.6 | E5: 11.7 | F5: 10.9 | G5: 10 | H5: 8.7 | I5: 8.2 | J5: 7.9 | K5: 7 | L5: 7.4
A6: Maternelle et élémentaire | B6: 34.2 | C6: 14 | D6: 13.5 | E6: 10.8 | F6: 10.1 | G6: 10 | H6: 9.3 | I6: 8.7 | J6: 8.1 | K6: 7.5 | L6: 7.9
A7: Collège | B7: 27.2 | C7: 14.3 | D7: 13.2 | E7: 11.5 | F7: 11.1 | G7: 10.5 | H7: 8.8 | I7: 8 | J7: 7.7 | K7: 6.9 | L7: 7.9
A8: Lycée général et technologique | B8: 9.3 | C8: 11.8 | D8: 12 | E8: 12 | F8: 10.7 | G8: 8.1 | H8: 8.4 | I8: 9.3 | J8: 9.2 | K8: 9 | L8: 9.5
A9: Lycée professionnel | B9: 11.2 | C9: 19.4 | D9: 16 | E9: 14.5 | F9: 12.7 | G9: 10.3 | H9: 7 | I9: 6.2 | J9: 6.7 | K9: 4.1 | L9: 3
A10: Supérieur (STS, CPGE et université) | B10: 22.1 | C10: 16.1 | D10: 8.4 | E10: 9.8 | F10: 8.9 | G10: 8.7 | H10: 9.1 | I10: 7.8 | J10: 9.3 | K10: 10 | L10: 11.9
A11: Étudiant cohabitant | B11: 19.4 | C11: 16.8 | D11: 8.8 | E11: 10.6 | F11: 8.9 | G11: 9 | H11: 9.5 | I11: 7.6 | J11: 9.5 | K11: 9.2 | L11: 10.1
A12: Étudiant non cohabitant | B12: 2.8 | C12: 11.1 | D12: 5.6 | E12: 4.3 | F12: 8.7 | G12: 6.7 | H12: 6 | I12: 9.7 | J12: 7.9 | K12: 15.7 | L12: 24.4
A13: Ensemble | B13: 104.9 | C13: 15 | D13: 12.5 | E13: 11.3 | F13: 10.5 | G13: 9.7 | H13: 8.8 | I13: 8.1 | J13: 8.2 | K13: 7.6 | L13: 8.4
A14: Lecture : sur une dépense d’éducation de 22,1 milliards d’euros dans le supérieur en 2018, 16,1 % sont versés aux ménages appartenant aux 10 % les plus modestes (niveau de vie usuel inférieur au 1er décile). Dans le supérieur, 19,4 milliards d’euros sont distribués aux étudiants cohabitants chez leurs parents, dont 16,8% aux 10 % les plus modestes.
A15: Champ : France.
A16: Source : Comptes nationaux distribués 2018 ; calcul des auteurs.

Sheet Figure 5
A1: Figure 5 - Services publics collectifs locaux par établissement public de coopération intercommunale (EPCI)
A2: en euros par unité de consommation
A3: EPCI | B3: Dépense collective locale
A4: 200000172 | B4: 1429.6
A5: 200000438 | B5: 752.3
A6: 200000545 | B6: 2229.5
A7: 200000628 | B7: 1230.2
A8: 200000800 | B8: 1132.2
A9: 200000925 | B9: 815.2
A10: 200000933 | B10: 856.9
A11: 200004802 | B11: 1005.7
A12: 200005932 | B12: 829.2
A13: 200005957 | B13: 885.3
A14: 200006682 | B14: 1208.7
A15: 200006716 | B15: 1594.1
... A1235: 249500513 | B1235: 1080.7
A1236: Note : les territoires non colorés n'ont pas de services publics locaux non individualisables tels que définis ici.
A1237: Lecture : les territoires les plus foncés sont mieux dotés de services publics locaux non individualisables (police, collectivités locales, équipements, etc.).
A1238: Champ : France.
A1239: Source : Insee, DADS et ERFS 2017 ; calcul des auteurs.

Sheet Figure 6
A1: Figure 6 - Prélèvements par dixième de niveau de vie usuel, en part du revenu avant transferts
J2: en % du revenu avant transferts
B3: Ensemble | C3: Inférieur à D1 | D3: D1 à D2 | E3: D2 à D3 | F3: D3 à D4 | G3: D4 à D5 | H3: D5 à D6 | I3: D6 à D7 | J3: D7 à D8 | K3: D8 à D9 | L3: Supérieur à D9
A4: Cotisations sociales | B4: 24.1 | C4: 22.3 | D4: 25.2 | E4: 25 | F4: 25.6 | G4: 26.8 | H4: 27.4 | I4: 27.6 | J4: 27.5 | K4: 26.7 | L4: 18.8
A5: Impôts sur les revenus et le patrimoine | B5: 12.5 | C5: 4.9 | D5: 5.9 | E5: 7.2 | F5: 8.6 | G5: 9.3 | H5: 10 | I5: 11.1 | J5: 12.4 | K5: 14.2 | L5: 16.6
A6: Impôt sur les sociétés | B6: 3 | C6: 0.4 | D6: 0.4 | E6: 0.3 | F6: 0.2 | G6: 0.2 | H6: 0.2 | I6: 0.4 | J6: 0.6 | K6: 0.7 | L6: 8.6
A7: Taxes sur la production et la consommation | B7: 16.4 | C7: 40.4 | D7: 29.3 | E7: 24.3 | F7: 21.5 | G7: 20 | H7: 18.5 | I7: 17.2 | J7: 16.2 | K7: 15.6 | L7: 9.6
A8: Taxes sur les produits | B8: 11 | C8: 29.3 | D8: 20.9 | E8: 16.9 | F8: 14.9 | G8: 13.7 | H8: 12.5 | I8: 11.4 | J8: 10.6 | K8: 10.3 | L8: 5.9
A9: Taxes sur la production | B9: 5.4 | C9: 11.1 | D9: 8.4 | E9: 7.3 | F9: 6.6 | G9: 6.3 | H9: 6 | I9: 5.8 | J9: 5.5 | K9: 5.3 | L9: 3.6
A10: Ensemble | B10: 56.1 | C10: 68.1 | D10: 60.7 | E10: 56.8 | F10: 56 | G10: 56.3 | H10: 56.1 | I10: 56.3 | J10: 56.7 | K10: 57.3 | L10: 53.6
A11: Lecture : les 10 % les plus modestes (niveau de vie usuel inférieur au 1er décile) contribuent en moyenne à hauteur de 29 % de leur revenu avant transferts au titre des taxes sur les produits et de 22 % au titre des cotisations sociales.
A12: Champ : France.
A13: Source : Comptes nationaux distribués 2018 ; calcul des auteurs.

Sheet Figure 7
A1: Figure 7 - Distribution du revenu national avant et après transferts, selon le niveau de vie usuel
J2: en euros par unité de consommation
B3: Ensemble | C3: Inférieur à D1 | D3: D1 à D2 | E3: D2 à D3 | F3: D3 à D4 | G3: D4 à D5 | H3: D5 à D6 | I3: D6 à D7 | J3: D7 à D8 | K3: D8 à D9 | L3: Supérieur à D9
A4: Revenu national net avant transferts par UC | B4: 42820 | C4: 10480 | D4: 15870 | E4: 21040 | F4: 25880 | G4: 31250 | H4: 36380 | I4: 42160 | J4: 49500 | K4: 60390 | L4: 133080
A5: Revenu national net après transferts par UC | B5: 42820 | C5: 28370 | D5: 31840 | E5: 33300 | F5: 34640 | G5: 36340 | H5: 38740 | I5: 41640 | J5: 44580 | K5: 50750 | L5: 87030
A6: Revenu disponible (après transferts) | B6: 29710 | C6: 11000 | D6: 15360 | E6: 18860 | F6: 21390 | G6: 23830 | H6: 26670 | I6: 29750 | J6: 33070 | K6: 39170 | L6: 76790
A7: Revenu avant redistribution usuelle | B7: 37430 | C7: 7130 | D7: 13220 | E7: 18730 | F7: 23150 | G7: 27320 | H7: 31590 | I7: 36890 | J7: 42630 | K7: 52650 | L7: 119000
A8: Redistribution élargie moyenne (solde des transferts publics) | B8: 0 | C8: 17890 | D8: 15980 | E8: 12260 | F8: 8760 | G8: 5090 | H8: 2360 | I8: -520 | J8: -4920 | K8: -9640 | L8: -46060
A9: 1. Bénéficiaires en moyenne à l'intérieur d'un dixième de population. Il peut cependant exister des perdants parmi cette catégorie de ménages.
A10: 2. Revenu disponible calculé à partir des comptes nationaux distribués. Il est différent du revenu disponible diffusé usuellement par l'Insee. Ce dernier contient notamment les allocations logement alors qu'elles ne sont pas comprises ici.
A11: Lecture : le revenu primaire élargi (avant transferts) des 10 % les plus aisés (niveau de vie usuel supérieur au 9e décile) s’élève à 133 080 euros par unité de consommation (UC) contre 10 480 euros par UC pour les 10 % les plus modestes (inférieur au 1er décile). Le niveau de vie élargi (après transferts) est égal à 87 030 euros en moyenne pour les 10 % les plus aisés contre 28 370 euros pour les plus modestes. Les personnes appartenant aux 10% les plus modestes sont en moyenne bénéficiaires de la redistribution (même s'il peut exister des perdants parmi cette catégorie de ménages).
A12: Champ : France.
A13: Source : Comptes nationaux distribués 2018 ; calcul des auteurs.

Sheet Figure 8
A1: Figure 8 - Décomposition de la contribution à la réduction des inégalités avant et après transferts
B3: en % du revenu national net | C3: Indice de Gini | F3: Palma T10/B40 | G3: Ratio (100-S80)/S20
C4: Niveau | D4: Contribution à la réduction en niveau | E4: Contribution à la réduction en %
A5: Revenu avant transferts | B5: 100 | C5: 0.381 | F5: 1.84 | G5: 7.57
A6: Taxes sur les produits et la production | B6: -16.4 | C6: 0.188 | D6: -0.032 | E6: -15.4 | F6: 0.66 | G6: 2.58
A7: Impôts sur les revenus et le patrimoine | B7: -15.5 | C7: 0.589 | D7: 0.032 | E7: 15.6 | F7: 6.27 | G7: 28.16
A8: Cotisations sociales | B8: -24.1 | C8: 0.34 | D8: -0.01 | E8: -4.8 | F8: 1.38 | G8: 6.69
A9: dont cotisations retraites | B9: -13 | C9: 0.376 | D9: -0.001 | E9: -0.3 | F9: 1.66 | G9: 10.48
A10: Revenu primaire après prélèvements | B10: 45.1 | C10: 0.416 | G10: 10.16
A11: Transferts en espèces | B11: 25.5 | C11: 0.11 | D11: 0.069 | E11: 33.4 | F11: 0.44 | G11: 1.82
A12: Retraites | B12: 16.9 | C12: 0.257 | D12: 0.021 | E12: 10.1 | F12: 0.79 | G12: 5.12
A13: Autres transferts sociaux en espèces | B13: 8.6 | C13: -0.177 | D13: 0.048 | E13: 23.3 | F13: 0.15 | G13: 0.46
A14: Revenu disponible1 | B14: 69.4 | C14: 0.293 | F14: 1.17 | G14: 4.54
A15: Transferts en nature | B15: 20.6 | C15: -0.124 | D15: 0.104 | E15: 50.4 | F15: 0.15 | G15: 0.57
A16: Dépenses collectives2 | B16: 7.8 | C16: -0.032 | D16: 0.032 | E16: 15.6 | F16: 0.22 | G16: 7.04
A17: Autres transferts | B17: 2.3 | C17: -0.005 | D17: 0.009 | E17: 4.3 | F17: 0.25 | G17: 1
A18: Niveau de vie élargi | B18: 100 | C18: 0.175 | D18: 0.206 | E18: 100 | F18: 0.79 | G18: 2.36
A19: 1. Y compris profit non distribués (encadré 3).
A20: 2. Y compris épargne des administrations publiques nette de consommation de capital fixe (CCF).
A21: Note : les indices de Gini sont calculés à partir des montants agrégés par dixième. Cette approximation se justifie par les propriétés linéaires de l’indicateur sur des variables continues. Aucun reclassement n'est réalisé selon les lignes du tableau, les dixièmes de population sont calculés à partir du revenu disponible par unité de consommation.
A22: Lecture : l'indice de Gini des impôts sur les revenus et le patrimoine est de 0,59, supérieur de 0,21 à celui du revenu avant transferts, ce qui indique que ce transfert est progressif. Il contribue à réduire les inégalités à hauteur de 0,03 (égal à 0,21 multiplié par le poids de ces impôts, 15,5%). Cela correspond à une contribution de 15,4% à la baisse de 0,21 de l'indice de Gini liée à la redistribution.
A23: Champ : France.
A24: Source : Comptes nationaux distribués 2018 ; calcul des auteurs

Sheet Figure 9
A1: Figure 9 - Décomposition de la redistribution élargie par catégorie de ménages
E2: en euros par unité de consommation
B3: Ensemble | C3: Pauvres (15 % des individus) | D3: Modestes (27% des individus) | E3: Médians (25% des individus) | F3: Plutôt aisés (23% des individus) | G3: Aisés (10% des individus)
A4: Transferts reçus en espèces hors retraites | B4: 3680 | C4: 6380 | D4: 4240 | E4: 3120 | F4: 2490 | G4: 2960
A5: Retraites | B5: 7220 | C5: 2070 | D5: 5090 | E5: 7500 | F5: 9540 | G5: 13280
A6: Transferts reçus en nature et dépenses collectives1 | B6: 12930 | C6: 17940 | D6: 11830 | E6: 10960 | F6: 11300 | G6: 18310
A7: Cotisations sociales | B7: -10340 | C7: -2630 | D7: -5550 | E7: -9720 | F7: -14450 | G7: -24930
A8: Impôts sur le revenu et le patrimoine | B8: -6650 | C8: -660 | D8: -1720 | E8: -3660 | F8: -7210 | G8: -33700
A9: Taxes sur la production et la consommation | B9: -7020 | C9: -4300 | D9: -5180 | E9: -6790 | F9: -8420 | G9: -12680
A10: Revenu national net avant transferts (RNNAV) | B10: 42820 | C10: 12170 | D10: 21620 | E10: 35630 | F10: 52150 | G10: 134830
A11: Revenu national net après transferts (RNNAP) | B11: 42820 | C11: 31770 | D11: 30780 | E11: 37330 | F11: 45500 | G11: 96770
A12: 1. Hors épargne nette et ajustements des autres comptes
A13: Lecture : le revenu primaire élargi moyen des individus pauvres avant transferts s’élève à 12 170 euros par UC et celui des individus modestes à 21 620 euros par UC, contre 52 150 euros par UC pour les individus plutôt aisés et 134 830 euros par UC pour les individus aisés. En moyenne, les individus médians bénéficient de 21 580 euros par UC de transferts et dépenses collectives et contribuent à hauteur de 20 170 euros par UC au titre des prélèvements.
A14: Champ : France.
A15: Source : Comptes nationaux distribués 2018 ; calcul des auteurs.

Sheet Figure complémentaire 1
A1: Figure complémentaire 1 - Comptes nationaux distribués pour la France en 2018 par dixième de niveau de vie usuel, par UC
B3: Part dans le revenu national net (en %) | C3: Moyenne (en milliards d'euros) | D3: Transferts par dixième de population, par UC
C4: en euros par UC | D4: ='Figure 2'!D4 -> Inférieur à D1 | E4: ='Figure 2'!E4 -> D1 à D2 | F4: ='Figure 2'!F4 -> D2 à D3 | G4: ='Figure 2'!G4 -> D3 à D4 | H4: ='Figure 2'!H4 -> D4 à D5 | I4: ='Figure 2'!I4 -> D5 à D6 | J4: ='Figure 2'!J4 -> D6 à D7 | K4: ='Figure 2'!K4 -> D7 à D8 | ... M4: ='Figure 2'!M4 -> Supérieur à D9
A5: Revenus primaires élargis | B5: 100 | C5: 42820 | D5: 10480 | E5: 15870 | F5: 21040 | G5: 25880 | H5: 31250 | I5: 36380 | J5: 42160 | K5: 49500 | L5: 60390 | M5: 133080
A6: dont : revenus salariaux | B6: 63.2 | C6: 27060 | D6: 4810 | E6: 9520 | F6: 13470 | G6: 17530 | H6: 21730 | I6: 25700 | J6: 29970 | K6: 35430 | L6: 41960 | M6: 69160
A7: revenus du patrimoine et mixtes1 | B7: 21.6 | C7: 9250 | D7: 1760 | E7: 2060 | F7: 2840 | G7: 3150 | H7: 3670 | I7: 4380 | J7: 5400 | K7: 6600 | L7: 9620 | M7: 52310
A8: Taxes sur les produits et la production2 | B8: -16.4 | C8: -7020 | D8: -4240 | E8: -4650 | F8: -5100 | G8: -5580 | H8: -6260 | I8: -6740 | J8: -7270 | K8: -8010 | L8: -9420 | M8: -12730
A9: dont : taxes sur la production | B9: 3.1 | C9: -1340 | D9: -350 | E9: -470 | F9: -660 | G9: -790 | H9: -1020 | I9: -1210 | J9: -1440 | K9: -1700 | L9: -2150 | M9: -3590
A10: taxes sur la consommation | B10: 11 | C10: -4690 | D10: -3070 | E10: -3320 | F10: -3570 | G10: -3860 | H10: -4290 | I10: -4550 | J10: -4810 | K10: -5270 | L10: -6190 | M10: -7910
A11: Impôts sur les revenus et le patrimoine2 | B11: 15.5 | C11: -6650 | D11: -570 | E11: -990 | F11: -1570 | G11: -2280 | H11: -2960 | I11: -3710 | J11: -4850 | K11: -6460 | L11: -9030 | M11: -33590
A12: dont : CSG | B12: 6.3 | C12: -2710 | D12: -290 | E12: -690 | F12: -1130 | G12: -1640 | H12: -2080 | I12: -2460 | J12: -2880 | K12: -3400 | L12: -4250 | M12: -8100
A13: impôt sur le revenu | B13: 4.2 | C13: -1790 | D13: -70 | E13: -30 | F13: -40 | G13: -130 | H13: -270 | I13: -530 | J13: -1040 | K13: -1800 | L13: -3010 | M13: -10850
A14: impôt sur les sociétés | B14: 3 | C14: -1290 | D14: -50 | E14: -60 | F14: -60 | G14: -40 | H14: -60 | I14: -70 | J14: -160 | K14: -300 | L14: -430 | M14: -11500
A15: Cotisations sociales2 | B15: 24.1 | C15: -10340 | D15: -2340 | E15: -4000 | F15: -5270 | G15: -6630 | H15: -8380 | I15: -9960 | J15: -11620 | K15: -13620 | L15: -16130 | M15: -24960
A16: dont : cotisations retraites | B16: 13 | C16: -5590 | D16: -590 | E16: -1650 | F16: -2520 | G16: -3440 | H16: -4540 | I16: -5550 | J16: -6580 | K16: -7900 | L16: -9290 | M16: -13520
... A28: Niveau de vie élargi (euros par UC) | B28: 100 | C28: 42820 | D28: 28370 | E28: 31840 | F28: 33300 | G28: 34640 | H28: 36340 | I28: 38740 | J28: 41640 | K28: 44580 | L28: 50750 | M28: 87030
A29: 1. Y compris PND (voir encadré 3).
A30: 2. Les lignes résiduelles "dont autres" ne sont pas affichées
A31: Lecture : les 10% les plus modestes (niveau de vie usuel inférieur au 1er décile) perçoivent 1,4 % des 774 milliards d'euros de revenus salariaux bruts reçus en France (soit 16 721 euros par UC). Ils ont un revenu avant transferts moyen de 10 477 euros par UC et un niveau de vie élargi (après transferts) de 28 369 euros.
A32: Champ : France.
A33: Source : Comptes nationaux distribués 2018 ; calcul des auteurs.

Sheet Figure complémentaire 2
A1: Figure complémentaire 2 - Comptes nationaux distribués pour la France en 2018 par dixième de niveau de vie usuel
K2: en milliard d'euros (Mds)
B3: Total | D3: Transferts par dixième de population (en Mds €)
B4: en % du RNN | C4: en Mds € | D4: ='[2]Figure 2'!D6 -> Inférieur à D1 | E4: ='[2]Figure 2'!E6 -> D1 à D2 | F4: ='[2]Figure 2'!F6 -> D2 à D3 | G4: ='[2]Figure 2'!G6 -> D3 à D4 | H4: ='[2]Figure 2'!H6 -> D4 à D5 | I4: ='[2]Figure 2'!I6 -> D5 à D6 | J4: ='[2]Figure 2'!J6 -> D6 à D7 | K4: ='[2]Figure 2'!K6 -> D7 à D8 | ... M4: ='[2]Figure 2'!M6 -> Supérieur à D9
A5: Revenus salariaux bruts (1) | B5: 63.2 | C5: 1252.8 | D5: 21.5 | E5: 43.6 | F5: 62.9 | G5: 82.4 | H5: 101.2 | I5: 118.3 | J5: 137.5 | K5: 164.7 | L5: 196.4 | M5: 324.2
A6: dont salaires nets | B6: 39.1 | C6: 774.2 | D6: 11.1 | E6: 25.3 | F6: 38.3 | G6: 51.2 | H6: 62.2 | I6: 72.5 | J6: 84.2 | K6: 101.4 | L6: 120.9 | M6: 207.2
A7: Revenus mixtes nets et du patrimoine (2) | B7: 15.8 | C7: 313.2 | D7: 7.5 | E7: 8.9 | F7: 12.7 | G7: 14.4 | H7: 16.6 | I7: 19.5 | J7: 23.4 | K7: 28 | L7: 41.1 | M7: 141.1
A8: dont : revenus mixtes nets | B8: 5.6 | C8: 111.7 | D8: 1.6 | E8: 2.7 | F8: 3.2 | G8: 3.3 | H8: 3.2 | I8: 4.4 | J8: 5.6 | K8: 7.2 | L8: 13.6 | M8: 67.1
A9: revenus nets de la propriété | B9: 4.3 | C9: 86.2 | D9: 0.8 | E9: 1 | F9: 1.6 | G9: 1.9 | H9: 2.4 | I9: 3.2 | J9: 4.4 | K9: 6 | L9: 10.8 | M9: 54.1
A10: loyers réels et fictifs nets des charges | B10: 5.8 | C10: 115.4 | D10: 5.1 | E10: 5.3 | F10: 7.9 | G10: 9.3 | H10: 11.1 | I10: 11.9 | J10: 13.4 | K10: 14.8 | L10: 16.7 | M10: 19.9
A11: Revenus des entreprises et ISBSLM bruts d'impôts (3) | B11: 5.8 | C11: 115.1 | D11: 0.4 | E11: 0.6 | F11: 0.5 | G11: 0.4 | H11: 0.5 | I11: 0.6 | J11: 1.4 | K11: 2.7 | L11: 3.9 | M11: 104.2
A12: dont : profits non distribués nets d'impôt sur les sociétés | B12: 1.5 | C12: 30 | D12: 0.1 | E12: 0.1 | F12: 0.1 | G12: 0.1 | H12: 0.1 | I12: 0.2 | J12: 0.4 | K12: 0.7 | L12: 1 | M12: 27.2
A13: impôt sur les sociétés | B13: 3 | C13: 59.6 | D13: 0.2 | E13: 0.3 | F13: 0.3 | G13: 0.2 | H13: 0.3 | I13: 0.3 | J13: 0.7 | K13: 1.4 | L13: 2 | M13: 53.9
A14: autres transferts des entreprises (fraude) | B14: 1.3 | C14: 25.5 | D14: 0.1 | E14: 0.1 | F14: 0.1 | G14: 0.1 | H14: 0.1 | I14: 0.1 | J14: 0.3 | K14: 0.6 | L14: 0.9 | M14: 23.1
A15: Revenu des facteurs (= 1+2+3) | B15: 84.8 | C15: 1681.2 | D15: 29.4 | E15: 53.1 | F15: 76.1 | G15: 97.2 | H15: 118.3 | I15: 138.5 | J15: 162.3 | K15: 195.4 | L15: 241.4 | M15: 569.5
A16: Revenu primaire des APU (4) | B16: 15.2 | C16: 301.1 | D16: 17.5 | E16: 19.7 | F16: 22.1 | G16: 24.4 | H16: 27.3 | I16: 29 | J16: 31.2 | K16: 34.8 | L16: 41.2 | M16: 54.4
... A68: Revenu national net après transferts (D=C+11+12+13) | B68: 100 | C68: 1982.3 | D68: 127 | E68: 146 | F68: 155.5 | G68: 162.8 | H68: 169.3 | I68: 178.4 | J68: 191 | K68: 207.2 | L68: 237.5 | M68: 408
A69: 1. Nommé aussi "Revenus primaires élargis" dans le dossier.
A70: 2. Y compris PND (voir encadré 3).
A71: Lecture : les 10% les plus modestes (niveau de vie usuel inférieur au 1er décile) perçoivent 21,5 milliards d'euros de revenus salariaux bruts sur les 1 253 milliards d'euros de revenus salariaux bruts reçus en France .
A72: Champ : France.
A73: Source : Comptes nationaux distribués 2018 ; calcul des auteurs.
